[
	{
		"id": 1,
		"title": "Приветствие",
		"color": "from-pink-500 to-purple-600",
		"icon": "👋",
		"theory": [
			{
				"type": "text",
				"header": "Нихао!",
				"content": "Самое популярное приветствие..."
			},
			{
				"type": "hanzi",
				"char": "你好",
				"pinyin": "nǐ hǎo",
				"translation": "Привет"
			}
		],
		"quizzes": [
			{
				"title": "Введение",
				"description": "Da",
				"questions": [
					{
						"id": "1",
						"type": "test",
						"question": "你好",
						"options": [
							"Привет",
							"Пока",
							"Ок",
							"Нет"
						],
						"correctAnswer": "Привет"
					},
					{
						"id": "2",
						"type": "listening",
						"audioText": "谢谢",
						"options": [
							"Спасибо",
							"Друг",
							"Дом",
							"Мир"
						],
						"correctAnswer": "Спасибо"
					}
				]
			},
			{
				"questions": [
					{
						"id": "2",
						"type": "blank",
						"taskText": "Какой-то вопрос",
						"sentence": "Очень [___] вопрос",
						"options": [
							"1",
							"2",
							"3",
							"4"
						],
						"correctAnswer": "3"
					}
				]
			}
		],
		"final": [
			{
				"id": "1",
				"type": "matching",
				"pairs": [
					{ "id": 1, "first": "1", "second": "1" },
					{ "id": 2, "first": "2", "second": "2" },
					{ "id": 3, "first": "3", "second": "3" },
					{ "id": 4, "first": "4", "second": "4" }
				],
				"correctAnswer": "Привет"
			}
		]
	}
]